rtl/core/pe_array/pe.sv
//=============================================================================
// Processing Element (PE)
// Basic compute unit with MAC operation for systolic array
//=============================================================================

module pe
    import npu_pkg::*;
#(
    parameter int DATA_WIDTH   = 8,
    parameter int WEIGHT_WIDTH = 8,
    parameter int ACC_WIDTH    = 32
)(
    input  logic                            clk,
    input  logic                            rst_n,
    
    // Control
    input  logic                            enable,
    input  logic                            clear_acc,
    input  logic                            load_weight,
    
    // Data flow (systolic)
    input  logic signed [DATA_WIDTH-1:0]    data_in,      // From left/top
    input  logic signed [WEIGHT_WIDTH-1:0]  weight_in,    // Weight to load
    output logic signed [DATA_WIDTH-1:0]    data_out,     // To right/bottom
    
    // Accumulator output
    output logic signed [ACC_WIDTH-1:0]     acc_out,
    output logic                            acc_valid
);

    //=========================================================================
    // Internal Registers
    //=========================================================================
    
    logic signed [WEIGHT_WIDTH-1:0]  weight_reg;
    logic signed [DATA_WIDTH-1:0]    data_reg;
    logic signed [ACC_WIDTH-1:0]     acc_reg;
    logic                            valid_reg;
    
    // MAC result
    logic signed [DATA_WIDTH+WEIGHT_WIDTH-1:0] mult_result;
    logic signed [ACC_WIDTH-1:0]               add_result;
    
    //=========================================================================
    // MAC Operation
    //=========================================================================
    
    // Multiply
    assign mult_result = data_in * weight_reg;
    
    // Accumulate
    assign add_result = acc_reg + {{(ACC_WIDTH-DATA_WIDTH-WEIGHT_WIDTH){mult_result[DATA_WIDTH+WEIGHT_WIDTH-1]}}, mult_result};
    
    //=========================================================================
    // Sequential Logic
    //=========================================================================
    
    always_ff @(posedge clk or negedge rst_n) begin
        if (!rst_n) begin
            weight_reg <= '0;
            data_reg   <= '0;
            acc_reg    <= '0;
            valid_reg  <= 1'b0;
        end else begin
            // Load weight
            if (load_weight) begin
                weight_reg <= weight_in;
            end
            
            // Clear accumulator
            if (clear_acc) begin
                acc_reg   <= '0;
                valid_reg <= 1'b0;
            end else if (enable) begin
                // Systolic data flow - pass data to next PE
                data_reg <= data_in;
                
                // MAC operation
                acc_reg   <= add_result;
                valid_reg <= 1'b1;
            end
        end
    end
    
    //=========================================================================
    // Outputs
    //=========================================================================
    
    assign data_out  = data_reg;
    assign acc_out   = acc_reg;
    assign acc_valid = valid_reg;

endmodule

verification/testbench/unit/tb_pe.sv
//=============================================================================
// PE Testbench
// Unit test for Processing Element
//=============================================================================

`timescale 1ns/1ps

module tb_pe;

    //=========================================================================
    // Parameters
    //=========================================================================
    
    parameter int DATA_WIDTH   = 8;
    parameter int WEIGHT_WIDTH = 8;
    parameter int ACC_WIDTH    = 32;
    parameter int CLK_PERIOD   = 10;
    
    //=========================================================================
    // Signals
    //=========================================================================
    
    logic                           clk;
    logic                           rst_n;
    logic                           enable;
    logic                           clear_acc;
    logic                           load_weight;
    logic signed [DATA_WIDTH-1:0]   data_in;
    logic signed [WEIGHT_WIDTH-1:0] weight_in;
    logic signed [DATA_WIDTH-1:0]   data_out;
    logic signed [ACC_WIDTH-1:0]    acc_out;
    logic                           acc_valid;
    
    //=========================================================================
    // DUT
    //=========================================================================
    
    pe #(
        .DATA_WIDTH   (DATA_WIDTH),
        .WEIGHT_WIDTH (WEIGHT_WIDTH),
        .ACC_WIDTH    (ACC_WIDTH)
    ) dut (
        .clk          (clk),
        .rst_n        (rst_n),
        .enable       (enable),
        .clear_acc    (clear_acc),
        .load_weight  (load_weight),
        .data_in      (data_in),
        .weight_in    (weight_in),
        .data_out     (data_out),
        .acc_out      (acc_out),
        .acc_valid    (acc_valid)
    );
    
    //=========================================================================
    // Clock Generation
    //=========================================================================
    
    initial begin
        clk = 0;
        forever #(CLK_PERIOD/2) clk = ~clk;
    end
    
    //=========================================================================
    // Test Stimulus
    //=========================================================================
    
    initial begin
        // Initialize
        rst_n       = 0;
        enable      = 0;
        clear_acc   = 0;
        load_weight = 0;
        data_in     = 0;
        weight_in   = 0;
        
        // Reset
        #(CLK_PERIOD * 5);
        rst_n = 1;
        #(CLK_PERIOD * 2);
        
        // Test 1: Load weight
        $display("Test 1: Load weight = 5");
        weight_in = 8'sd5;
        load_weight = 1;
        #CLK_PERIOD;
        load_weight = 0;
        
        // Test 2: MAC operation
        $display("Test 2: MAC operations");
        clear_acc = 1;
        #CLK_PERIOD;
        clear_acc = 0;
        
        // data_in = 3, weight = 5 => acc = 15
        data_in = 8'sd3;
        enable = 1;
        #CLK_PERIOD;
        $display("  3 * 5 = 15, acc_out = %0d", acc_out);
        
        // data_in = 4, weight = 5 => acc = 15 + 20 = 35
        data_in = 8'sd4;
        #CLK_PERIOD;
        $display("  4 * 5 = 20, acc_out = %0d (expected 35)", acc_out);
        
        // data_in = -2, weight = 5 => acc = 35 - 10 = 25
        data_in = -8'sd2;
        #CLK_PERIOD;
        $display("  -2 * 5 = -10, acc_out = %0d (expected 25)", acc_out);
        
        enable = 0;
        
        // Test 3: Clear accumulator
        $display("Test 3: Clear accumulator");
        clear_acc = 1;
        #CLK_PERIOD;
        clear_acc = 0;
        $display("  After clear, acc_out = %0d (expected 0)", acc_out);
        
        // Test 4: Negative weight
        $display("Test 4: Negative weight = -3");
        weight_in = -8'sd3;
        load_weight = 1;
        #CLK_PERIOD;
        load_weight = 0;
        
        data_in = 8'sd7;
        enable = 1;
        #CLK_PERIOD;
        $display("  7 * (-3) = -21, acc_out = %0d", acc_out);
        
        enable = 0;
        
        // End simulation
        #(CLK_PERIOD * 10);
        $display("\n========================================");
        $display("All tests completed!");
        $display("========================================\n");
        $finish;
    end
    
    //=========================================================================
    // VCD Dump
    //=========================================================================
    
    initial begin
        $dumpfile("tb_pe.vcd");
        $dumpvars(0, tb_pe);
    end

endmodule

tb_pe.vcd
$date
	Wed Jan  7 01:44:23 2026
$end
$version
	Icarus Verilog
$end
$timescale
	1ps
$end
$scope module tb_pe $end
$var wire 8 ! data_out [7:0] $end
$var wire 1 " acc_valid $end
$var wire 32 # acc_out [31:0] $end
$var reg 1 $ clear_acc $end
$var reg 1 % clk $end
$var reg 8 & data_in [7:0] $end
$var reg 1 ' enable $end
$var reg 1 ( load_weight $end
$var reg 1 ) rst_n $end
$var reg 8 * weight_in [7:0] $end
$scope module dut $end
$var wire 32 + acc_out [31:0] $end
$var wire 1 " acc_valid $end
$var wire 1 $ clear_acc $end
$var wire 1 % clk $end
$var wire 8 , data_in [7:0] $end
$var wire 8 - data_out [7:0] $end
$var wire 1 ' enable $end
$var wire 1 ( load_weight $end
$var wire 1 ) rst_n $end
$var wire 8 . weight_in [7:0] $end
$var wire 16 / mult_result [15:0] $end
$var wire 32 0 add_result [31:0] $end
$var reg 32 1 acc_reg [31:0] $end
$var reg 8 2 data_reg [7:0] $end
$var reg 1 3 valid_reg $end
$var reg 8 4 weight_reg [7:0] $end
$upscope $end
$upscope $end
$enddefinitions $end
#0
$dumpvars
b0 4
03
b0 2
b0 1
b0 0
b0 /
b0 .
b0 -
b0 ,
b0 +
b0 *
0)
0(
0'
b0 &
0%
0$
b0 #
0"
b0 !
$end
#5000
1%
#10000
0%
#15000
1%
#20000
0%
#25000
1%
#30000
0%
#35000
1%
#40000
0%
#45000
1%
#50000
0%
1)
#55000
1%
#60000
0%
#65000
1%
#70000
0%
1(
b101 *
b101 .
#75000
b101 4
1%
#80000
0%
1$
0(
#85000
1%
#90000
0%
1'
b1111 0
b1111 /
b11 &
b11 ,
0$
#95000
1"
13
b11110 0
b1111 #
b1111 +
b1111 1
b11 !
b11 -
b11 2
1%
#100000
0%
b100011 0
b10100 /
b100 &
b100 ,
#105000
b110111 0
b100011 #
b100011 +
b100011 1
b100 !
b100 -
b100 2
1%
#110000
0%
b11001 0
b1111111111110110 /
b11111110 &
b11111110 ,
#115000
b1111 0
b11001 #
b11001 +
b11001 1
b11111110 !
b11111110 -
b11111110 2
1%
#120000
0%
1$
0'
#125000
0"
03
b11111111111111111111111111110110 0
b0 #
b0 +
b0 1
1%
#130000
0%
1(
b11111101 *
b11111101 .
0$
#135000
b110 0
b110 /
b11111101 4
1%
#140000
0%
1'
b11111111111111111111111111101011 0
b1111111111101011 /
b111 &
b111 ,
0(
#145000
1"
13
b11111111111111111111111111010110 0
b11111111111111111111111111101011 #
b11111111111111111111111111101011 +
b11111111111111111111111111101011 1
b111 !
b111 -
b111 2
1%
#150000
0%
0'
